{
	"animations": [
		{
			"offsets": [
				99,
				-110
			],
			"loop": false,
			"fps": 24,
			"anim": "danceLeft",
			"indices": [
				30,
				0,
				1,
				2,
				3,
				4,
				5,
				6,
				7,
				8,
				9,
				10,
				11,
				12,
				13,
				14
			],
			"name": "chica"
		},
		{
			"offsets": [
				100,
				-110
			],
			"loop": false,
			"fps": 24,
			"anim": "danceRight",
			"indices": [
				15,
				16,
				17,
				18,
				19,
				20,
				21,
				22,
				23,
				24,
				25,
				26,
				27,
				28,
				29
			],
			"name": "chica"
		},
		{
			"offsets": [
				100,
				-110
			],
			"indices": [
				17,
				18,
				26,
				27
			],
			"fps": 24,
			"anim": "danceLeft-alt",
			"loop": false,
			"name": "chica"
		},
		{
			"offsets": [
				100,
				-110
			],
			"indices": [
				17,
				18,
				26,
				27
			],
			"fps": 24,
			"anim": "danceRight-alt",
			"loop": false,
			"name": "chica"
		}
	],
	"no_antialiasing": false,
	"image": "characters/Chica",
	"position": [
		0,
		0
	],
	"healthicon": "gf",
	"flip_x": false,
	"healthbar_colors": [
		165,
		0,
		-2147483648
	],
	"camera_position": [
		-110,
		270
	],
	"sing_duration": 4,
	"scale": 0.7
}